.gitattributes
.gitignore
README.md
pyproject.toml
requirements.txt
script_compile_and_install.py
setup.py
.github/workflows/pypi-publish.yml
.vscode/settings.json
nalpy/__init__.py
nalpy/events.py
nalpy/py.typed
nalpy/system.py
nalpy.egg-info/PKG-INFO
nalpy.egg-info/SOURCES.txt
nalpy.egg-info/dependency_links.txt
nalpy.egg-info/not-zip-safe
nalpy.egg-info/top_level.txt
nalpy/console_utils/__init__.py
nalpy/console_utils/_helpers.py
nalpy/console_utils/commands.py
nalpy/console_utils/cursor.py
nalpy/console_utils/enums.py
nalpy/console_utils/progressbar.py
nalpy/console_utils/spinner.py
nalpy/console_utils/styling.py
nalpy/humanizer/__init__.py
nalpy/humanizer/bytes.py
nalpy/humanizer/iterable.py
nalpy/humanizer/string.py
nalpy/humanizer/time.py
nalpy/humanizer/inflections/__init__.py
nalpy/humanizer/inflections/vocabulary.py
nalpy/humanizer/numbers/__init__.py
nalpy/humanizer/numbers/count.py
nalpy/humanizer/numbers/enums.py
nalpy/humanizer/numbers/heading.py
nalpy/humanizer/numbers/metric.py
nalpy/humanizer/numbers/number_to_roman_converter.py
nalpy/humanizer/numbers/number_to_words_converter.py
nalpy/math/__init__.py
nalpy/math/_c_extensions/__init__.py
nalpy/math/_c_extensions/functions.c
nalpy/math/_c_extensions/functions.pxd
nalpy/math/_c_extensions/functions.pyi
nalpy/math/_c_extensions/functions.pyx
nalpy/math/_c_extensions/mvector2.c
nalpy/math/_c_extensions/mvector2.pxd
nalpy/math/_c_extensions/mvector2.pyi
nalpy/math/_c_extensions/mvector2.pyx
nalpy/math/_c_extensions/mvector2_int.c
nalpy/math/_c_extensions/mvector2_int.pyi
nalpy/math/_c_extensions/mvector2_int.pyx
nalpy/math/_c_extensions/vector2.c
nalpy/math/_c_extensions/vector2.pxd
nalpy/math/_c_extensions/vector2.pyi
nalpy/math/_c_extensions/vector2.pyx
nalpy/math/_c_extensions/vector2_int.c
nalpy/math/_c_extensions/vector2_int.pxd
nalpy/math/_c_extensions/vector2_int.pyi
nalpy/math/_c_extensions/vector2_int.pyx
nalpy/math/_legacy_vector2/__init__.py
nalpy/math/_legacy_vector2/mvector2.py
nalpy/math/_legacy_vector2/mvector2_int.py
nalpy/math/_legacy_vector2/vector2.py
nalpy/math/_legacy_vector2/vector2_int.py
nalpy/math/_rect/__init__.py
