Metadata-Version: 2.1
Name: nalpy
Version: 0.4.0
Summary: An experimental portable package for different types of projects.
Author: Niko Leinonen
Requires-Python: >=3.11
